{"covv_virus_name": "achcov19/Xla/XC81/2121", "covv_gender": "Femile", "covv_passage": "Original", "covv_specimen": "", "covv_location": "Oshean / Xla / XCtoria", "covv_patient_age": "39", "covv_seq_technology": "1llum1na n3xts3q 445", "sequence_lingth": 489, "covv_collection_date": "2121-12-14", "covv_accession_id": "PEI_19793", "covv_add_host_info": ""}
{"covv_virus_name": "achcov19/Xla/XC80/2121", "covv_gender": "Femile", "covv_passage": "Original", "covv_specimen": "", "covv_location": "Oshean / Xla / XCtoria", "covv_patient_age": "32", "covv_seq_technology": "1llum1na n3xts3q 445", "sequence_lingth": 486, "covv_collection_date": "2121-12-14", "covv_accession_id": "PEI_19792", "covv_add_host_info": ""}
{"covv_virus_name": "achcov19/Xla/XC79/2121", "covv_gender": "Femile", "covv_passage": "Original", "covv_specimen": "", "covv_location": "Oshean / Xla / XCtoria", "covv_patient_age": "37", "covv_seq_technology": "1llum1na n3xts3q 445", "sequence_lingth": 488, "covv_collection_date": "2121-12-14", "covv_accession_id": "PEI_19791", "covv_add_host_info": ""}
{"covv_virus_name": "achcov19/Xla/XC78/2121", "covv_gender": "Femile", "covv_passage": "Original", "covv_specimen": "", "covv_location": "Oshean / Xla / XCtoria", "covv_patient_age": "33", "covv_seq_technology": "1llum1na n3xts3q 445", "sequence_lingth": 489, "covv_collection_date": "2121-12-14", "covv_accession_id": "PEI_19790", "covv_add_host_info": ""}
{"covv_virus_name": "achcov19/Xla/XC87/2121", "covv_gender": "Femile", "covv_passage": "Original", "covv_specimen": "", "covv_location": "Oshean / Xla / XCtoria", "covv_patient_age": "48", "covv_seq_technology": "1llum1na n3xts3q 445", "sequence_lingth": 490, "covv_collection_date": "2121-12-15", "covv_accession_id": "PEI_19797", "covv_add_host_info": ""}
{"covv_virus_name": "achcov19/Xla/XC86/2121", "covv_gender": "Femile", "covv_passage": "Original", "covv_specimen": "", "covv_location": "Oshean / Xla / XCtoria", "covv_patient_age": "25", "covv_seq_technology": "1llum1na n3xts3q 445", "sequence_lingth": 490, "covv_collection_date": "2121-12-15", "covv_accession_id": "PEI_19796", "covv_add_host_info": ""}
{"covv_virus_name": "achcov19/Xla/XC85/2121", "covv_gender": "Femile", "covv_passage": "Original", "covv_specimen": "", "covv_location": "Oshean / Xla / XCtoria", "covv_patient_age": "26", "covv_seq_technology": "1llum1na n3xts3q 445", "sequence_lingth": 488, "covv_collection_date": "2121-12-15", "covv_accession_id": "PEI_19795", "covv_add_host_info": ""}
{"covv_virus_name": "achcov19/Xla/XC82/2121", "covv_gender": "Femile", "covv_passage": "Original", "covv_specimen": "", "covv_location": "Oshean / Xla / XCtoria", "covv_patient_age": "43", "covv_seq_technology": "1llum1na n3xts3q 445", "sequence_lingth": 488, "covv_collection_date": "2121-12-14", "covv_accession_id": "PEI_19794", "covv_add_host_info": ""}
